{
  "questions": [
    {
      "text": "What is the capital of France?",
      "answer": "Paris"
    },
    {
      "text": "Which planet is known as the Red Planet?",
      "answer": "Mars"
    },
    {
      "text": "What is the largest mammal in the world?",
      "answer": "Blue Whale"
    },
    {
      "text": "Who painted the Mona Lisa?",
      "answer": "Leonardo da Vinci"
    },
    {
      "text": "What is the chemical symbol for gold?",
      "answer": "Au"
    }
  ]
}
